{
  "name": "Zafferano-patea tall carafe_gray.jpg",
  "bucket": "edievo-project.firebasestorage.app",
  "metageneration": 1,
  "generation": 1765801622362,
  "contentType": "image/jpeg",
  "storageClass": "STANDARD",
  "contentDisposition": "inline",
  "downloadTokens": [
    "c04b4bc3-d917-4966-916c-5deca83ec862"
  ],
  "etag": "kbauXD549MKnSONqHG0e8USnnNc",
  "customMetadata": {},
  "timeCreated": "2025-12-15T12:27:02.362Z",
  "updated": "2025-12-15T12:27:02.362Z",
  "size": 28219,
  "md5Hash": "erImgpI+WCnxQ/f3fkITbw==",
  "crc32c": "2370203546"
}