{
  "name": "Zafferano-patea tall convex vase_blue.jpg",
  "bucket": "edievo-project.firebasestorage.app",
  "metageneration": 1,
  "generation": 1765801617612,
  "contentType": "image/jpeg",
  "storageClass": "STANDARD",
  "contentDisposition": "inline",
  "downloadTokens": [
    "347179af-2d52-4f0a-9fae-6a5fc28f5490"
  ],
  "etag": "9KkXQujNXP/q1+6Oaq1hWGl4oFw",
  "customMetadata": {},
  "timeCreated": "2025-12-15T12:26:57.612Z",
  "updated": "2025-12-15T12:26:57.612Z",
  "size": 22325,
  "md5Hash": "/Sva+uU8WEJeUU71pUx+zg==",
  "crc32c": "3203662668"
}