{
  "name": "Officine Gullo-draining rack 25 cm_brass stainless steel.jpg",
  "bucket": "edievo-project.firebasestorage.app",
  "metageneration": 1,
  "generation": 1765801620969,
  "contentType": "image/jpeg",
  "storageClass": "STANDARD",
  "contentDisposition": "inline",
  "downloadTokens": [
    "5cb342fd-be54-4572-91cc-3a4f5d35c627"
  ],
  "etag": "drZ1oZ8U3oZWq7GD9/3+mIgfn7U",
  "customMetadata": {},
  "timeCreated": "2025-12-15T12:27:00.969Z",
  "updated": "2025-12-15T12:27:00.969Z",
  "size": 88622,
  "md5Hash": "3STIGxbefcUHIC51/ecW2w==",
  "crc32c": "3619767222"
}