{
  "name": "slamp-nuvem led spotlight.jpg",
  "bucket": "edievo-project.firebasestorage.app",
  "metageneration": 1,
  "generation": 1765801610181,
  "contentType": "image/jpeg",
  "storageClass": "STANDARD",
  "contentDisposition": "inline",
  "downloadTokens": [
    "4decff5d-81d2-4200-a9d4-e44d8e7f70bd"
  ],
  "etag": "NUJst3jRlQJ6mEysAGFfaydQzNA",
  "customMetadata": {},
  "timeCreated": "2025-12-15T12:26:50.181Z",
  "updated": "2025-12-15T12:26:50.181Z",
  "size": 44242,
  "md5Hash": "mUBK1tBi/+utWL6+4b5J3A==",
  "crc32c": "813492956"
}