{
  "name": "Pianca-Peonia Sofa.jpeg",
  "bucket": "edievo-project.firebasestorage.app",
  "metageneration": 1,
  "generation": 1765801626205,
  "contentType": "image/jpeg",
  "storageClass": "STANDARD",
  "contentDisposition": "inline",
  "downloadTokens": [
    "8f5c1ce7-1170-40ef-a804-05cff9942271"
  ],
  "etag": "F2NTWGRJm02uZJTf8nUdPhRh0fY",
  "customMetadata": {},
  "timeCreated": "2025-12-15T12:27:06.205Z",
  "updated": "2025-12-15T12:27:06.205Z",
  "size": 50957,
  "md5Hash": "yjxa+BwgwTHEsf3ZUMFE2w==",
  "crc32c": "1383653162"
}